[[{"__type__":"cc.Prefab","_name":"ClearEffect_Bubble_Back","data":{"__id__":1}},{"__type__":"cc.Node","_name":"BubbleEffect","_children":[{"__id__":2}],"_components":[{"__type__":"a94f6q6ywJKyIwexIJ/NTD+","node":{"__id__":1},"awakeAudio":{"__uuid__":"b6WyW/xCdPkrebX0u5QD6U"}}],"_prefab":{"__type__":"cc.PrefabInfo","root":{"__id__":1},"asset":{"__uuid__":"04awyrCEtI7q84PzG8dX8b"},"fileId":"82Ifwf0VFG9qNv798deTMP"},"_trs":{"__type__":"TypedArray","ctor":"Float64Array","array":[0,0,0,0,0,0,1,1,1,1]}},{"__type__":"cc.Node","_name":"Effect_CharacterAni_Bubble","_parent":{"__id__":1},"_components":[{"__type__":"cc.ParticleSystem","node":{"__id__":2},"_materials":[{"__uuid__":"ecpdLyjvZBwrvm+cedCcQy"}],"_custom":{"custom":false},"_file":{"__uuid__":"be6iz+eAZA661wXwB0QsRq"},"_spriteFrame":{"__uuid__":"9c5cFajMpIM46M2By7h/cj"},"totalParticles":15,"emissionRate":24.666666666666668,"life":1.5,"lifeVar":0.5,"_startColor":{"__type__":"cc.Color","r":255,"g":255,"b":255},"_startColorVar":{"__type__":"cc.Color","b":63},"_endColor":{"__type__":"cc.Color","r":255,"g":255,"b":255},"_endColorVar":{"__type__":"cc.Color","a":0},"angle":0,"angleVar":0,"startSize":100,"startSizeVar":20,"endSize":120,"endSizeVar":120,"posVar":{"__type__":"cc.Vec2","x":500,"y":900},"gravity":{"__type__":"cc.Vec2","y":150},"speed":-10,"speedVar":10,"tangentialAccel":0,"startRadius":100,"endRadius":200}],"_prefab":{"__type__":"cc.PrefabInfo","root":{"__id__":1},"asset":{"__uuid__":"04awyrCEtI7q84PzG8dX8b"},"fileId":"f6Ax3dKCFI0p9kH7AUZBJM"},"_trs":{"__type__":"TypedArray","ctor":"Float64Array","array":[0,0,0,0,0,0,1,1,1,1]}}],[{"__type__":"cc.Prefab","_name":"bony","data":{"__id__":1}},{"__type__":"cc.Node","_name":"bony","_components":[{"__type__":"sp.Skeleton","node":{"__id__":1},"_materials":[{"__uuid__":"7a/QZLET9IDreTiBfRn2PD"}],"defaultSkin":"default","defaultAnimation":"Clear_2_star","_preCacheMode":0,"loop":false,"_animationName":"Clear_2_star","_playTimes":1,"_N$skeletonData":{"__uuid__":"9aLGnRZ/RF07aG7b7T6niC"}},{"__type__":"86dc4nEm59BWrr2WoC5IuiM","node":{"__id__":1},"animationName":"Clear_2_star"}],"_prefab":{"__type__":"cc.PrefabInfo","root":{"__id__":1},"asset":{"__uuid__":"059o1FXilPhrzACZyhgIPs"},"fileId":"c3/x1KtnRBNZRhpJFEvfSt"},"_contentSize":{"__type__":"cc.Size","width":728.62,"height":1393.78},"_trs":{"__type__":"TypedArray","ctor":"Float64Array","array":[0,0,0,0,0,0,1,1,1,1]}}],{"__type__":"cc.AudioClip","_name":"UI_Combo01","_native":".mp3","duration":0.261224,"loadMode":1},{"__type__":"cc.AnimationClip","_name":"Landing","_duration":0.16666666666666666,"curveData":{"paths":{"Icon":{"props":{"y":[{"frame":0,"value":0},{"frame":0.08333333333333333,"value":-10},{"frame":0.16666666666666666,"value":0}]}}}}},{"__type__":"cc.AudioClip","_name":"UI_Count","_native":".mp3","duration":0.783673,"loadMode":1},{"__type__":"cc.AudioClip","_name":"UI_GameClear","_native":".mp3","duration":3.056327,"loadMode":1},{"__type__":"cc.SpriteFrame","content":{"name":"07_Balloon_Red","texture":"1eHDtbqPhHnLxU0Gi7tn1+","rect":[105,0,292,499],"offset":[1,0.5],"originalSize":[500,500],"capInsets":[0,0,0,0]}},{"__type__":"cc.AnimationClip","_name":"TouchBegan","_duration":0.16666666666666666,"curveData":{"paths":{"Icon":{"props":{"scale":[{"frame":0,"value":{"__type__":"cc.Vec2","x":1,"y":1}},{"frame":0.05,"value":{"__type__":"cc.Vec2","x":1.1,"y":1.1}},{"frame":0.16666666666666666,"value":{"__type__":"cc.Vec2","x":0.9,"y":0.9}}]}}}}},[{"__type__":"cc.Prefab","_name":"Bear_Animation","data":{"__id__":1}},{"__type__":"cc.Node","_name":"Bear_Animation","_components":[{"__type__":"sp.Skeleton","node":{"__id__":1},"_materials":[{"__uuid__":"7a/QZLET9IDreTiBfRn2PD"}],"defaultSkin":"default","_preCacheMode":0,"loop":false,"_animationName":"Clear","_playTimes":1,"_N$skeletonData":{"__uuid__":"52xOflAqhKXZVnHQkhj+Bl"}},{"__type__":"86dc4nEm59BWrr2WoC5IuiM","node":{"__id__":1},"type":2,"animationName":"Clear"}],"_prefab":{"__type__":"cc.PrefabInfo","root":{"__id__":1},"asset":{"__uuid__":"46jZVji5FMer7Udqgy+qYV"},"fileId":"861+Pei51OBb9WA9IAs3k0"},"_contentSize":{"__type__":"cc.Size","width":617,"height":696},"_trs":{"__type__":"TypedArray","ctor":"Float64Array","array":[0,0,0,0,0,0,1,1,1,1]}}],[{"__type__":"cc.Prefab","_name":"ClearEffect_Flower_Front","data":{"__id__":1}},{"__type__":"cc.Node","_name":"ClearEffect_Flower_Front","_children":[{"__id__":2}],"_components":[{"__type__":"a94f6q6ywJKyIwexIJ/NTD+","node":{"__id__":1},"awakeAudio":{"__uuid__":"03E4jAvFdId69RXDEndz7X"}}],"_prefab":{"__type__":"cc.PrefabInfo","root":{"__id__":1},"asset":{"__id__":0},"fileId":"6eU0di4+dJ15hMij1e/U6L"},"_trs":{"__type__":"TypedArray","ctor":"Float64Array","array":[0,0,0,0,0,0,1,1,1,1]}},{"__type__":"cc.Node","_name":"Effect_CharacterAni_Flower","_parent":{"__id__":1},"_children":[{"__id__":3}],"_components":[{"__type__":"cc.ParticleSystem","node":{"__id__":2},"_materials":[{"__uuid__":"ecpdLyjvZBwrvm+cedCcQy"}],"_custom":true,"_file":{"__uuid__":"a0dQhjCDNC1bnHVs90D9Hw"},"_spriteFrame":{"__uuid__":"8dAjeDPC1Fya0dwmN9d9/8"},"totalParticles":4,"emissionRate":2,"life":3,"lifeVar":1,"_startColor":{"__type__":"cc.Color","r":255,"g":255,"b":255},"_startColorVar":{"__type__":"cc.Color","a":0},"_endColor":{"__type__":"cc.Color","r":255,"g":255,"b":255},"_endColorVar":{"__type__":"cc.Color","a":0},"angleVar":80,"startSize":100,"startSizeVar":50,"endSize":150,"endSizeVar":30,"startSpin":180,"endSpin":40,"posVar":{"__type__":"cc.Vec2","x":800},"gravity":{"__type__":"cc.Vec2","y":-300},"speed":0,"speedVar":0,"tangentialAccel":130,"tangentialAccelVar":40}],"_prefab":{"__type__":"cc.PrefabInfo","root":{"__id__":1},"asset":{"__id__":0},"fileId":"7c0loyRT1Gi4ttmXCepMa2"},"_trs":{"__type__":"TypedArray","ctor":"Float64Array","array":[-71.614,1011.849,0,0,0,0,1,1,1,1]}},{"__type__":"cc.Node","_name":"Effect_CharacterAni_Flower","_parent":{"__id__":2},"_components":[{"__type__":"cc.ParticleSystem","node":{"__id__":3},"_materials":[{"__uuid__":"ecpdLyjvZBwrvm+cedCcQy"}],"_custom":true,"_spriteFrame":{"__uuid__":"58oX5pWf9IdarG98tVVzlJ"},"totalParticles":6,"emissionRate":2,"life":3,"lifeVar":1,"_startColor":{"__type__":"cc.Color","r":255,"g":255,"b":255},"_startColorVar":{"__type__":"cc.Color","a":0},"_endColor":{"__type__":"cc.Color","r":255,"g":255,"b":255},"_endColorVar":{"__type__":"cc.Color","a":0},"angle":70,"angleVar":29,"startSize":80,"startSizeVar":15,"endSize":50,"endSizeVar":20,"startSpin":120,"startSpinVar":40,"endSpin":270,"endSpinVar":40,"posVar":{"__type__":"cc.Vec2","x":800},"_positionType":2,"positionType":2,"gravity":{"__type__":"cc.Vec2","y":-450},"speed":40,"speedVar":0,"tangentialAccel":140,"tangentialAccelVar":50}],"_prefab":{"__type__":"cc.PrefabInfo","root":{"__id__":1},"asset":{"__id__":0},"fileId":"f8A83ny61NQp6/adJCfeUO"},"_trs":{"__type__":"TypedArray","ctor":"Float64Array","array":[5.261,0,0,0,0,0,1,1,1,1]}}],{"__type__":"cc.AudioClip","_name":"UI_Combo02","_native":".mp3","duration":0.261224,"loadMode":1},{"__type__":"cc.AnimationClip","_name":"level_readystart","_duration":2,"curveData":{"paths":{"test_text_start":{"props":{"scale":[{"frame":0.9166666666666666,"value":{"__type__":"cc.Vec2"},"curve":[0.18,0.89,0.31,1.21]},{"frame":1.1666666666666667,"value":{"__type__":"cc.Vec2","x":1,"y":1},"curve":[0.6,-0.27,0.73,0.04]},{"frame":1.6666666666666667,"value":{"__type__":"cc.Vec2","x":1,"y":1}},{"frame":1.9166666666666667,"value":{"__type__":"cc.Vec2"}}]}},"shadow":{"props":{"opacity":[{"frame":1.75,"value":200},{"frame":2,"value":0}]}},"test_text_ready":{"props":{"scale":[{"frame":0,"value":{"__type__":"cc.Vec2"},"curve":[0.18,0.89,0.31,1.21]},{"frame":0.25,"value":{"__type__":"cc.Vec2","x":1,"y":1}},{"frame":0.75,"value":{"__type__":"cc.Vec2","x":1,"y":1}},{"frame":1,"value":{"__type__":"cc.Vec2"}}]}}}},"events":[{"frame":1.1666666666666667,"func":"handleAnimationEvent","params":["go"]},{"frame":2,"func":"handleAnimationEvent","params":["end"]}]},{"__type__":"cc.SpriteFrame","content":{"name":"07_Balloon_Blue","texture":"e4uO01RoRG64BvdICpFCgm","rect":[105,0,292,499],"offset":[1,0.5],"originalSize":[500,500],"capInsets":[0,0,0,0]}},{"__type__":"cc.AudioClip","_name":"UI_Combo03","_native":".mp3","duration":0.261224,"loadMode":1},{"__type__":"cc.AudioClip","_name":"UI_Start","_native":".mp3","duration":0.339592,"loadMode":1},{"__type__":"cc.AudioClip","_name":"UI_Combo05","_native":".mp3","duration":0.20898,"loadMode":1},{"__type__":"cc.AudioClip","_name":"UI_BlockMatch","_native":".mp3","duration":0.391837,"loadMode":1},{"__type__":"cc.AnimationClip","_name":"TouchEnd","_duration":0.16666666666666666,"curveData":{"paths":{"Icon":{"props":{"scale":[{"frame":0,"value":{"__type__":"cc.Vec2","x":0.9,"y":0.9}},{"frame":0.05,"value":{"__type__":"cc.Vec2","x":1.1,"y":1.1}},{"frame":0.16666666666666666,"value":{"__type__":"cc.Vec2","x":1,"y":1}}]}}}}},{"__type__":"cc.SpriteFrame","content":{"name":"07_Balloon_Yellow","texture":"94VUPqBPpEerDr7yoCFO8I","rect":[105,0,292,499],"offset":[1,0.5],"originalSize":[500,500],"capInsets":[0,0,0,0]}},{"__type__":"cc.AudioClip","_name":"UI_BlockMiss","_native":".mp3","duration":0.10449,"loadMode":1},{"__type__":"cc.AudioClip","_name":"UI_Combo04","_native":".mp3","duration":0.261224,"loadMode":1},[{"__type__":"cc.Prefab","_name":"ClearEffect_Flower_Back","data":{"__id__":1}},{"__type__":"cc.Node","_name":"FlowerEffect","_children":[{"__id__":2}],"_components":[{"__type__":"a94f6q6ywJKyIwexIJ/NTD+","node":{"__id__":1},"awakeAudio":{"__uuid__":"03E4jAvFdId69RXDEndz7X"}}],"_prefab":{"__type__":"cc.PrefabInfo","root":{"__id__":1},"asset":{"__uuid__":"c2AyW62rBJVYuleZaINKoX"},"fileId":"9eZNf2NC9DqaA0CA9DmZbU"},"_trs":{"__type__":"TypedArray","ctor":"Float64Array","array":[0,0,0,0,0,0,1,1,1,1]}},{"__type__":"cc.Node","_name":"Effect_CharacterAni_Flower","_parent":{"__id__":1},"_children":[{"__id__":3}],"_components":[{"__type__":"cc.ParticleSystem","node":{"__id__":2},"_materials":[{"__uuid__":"ecpdLyjvZBwrvm+cedCcQy"}],"_custom":true,"_file":{"__uuid__":"a0dQhjCDNC1bnHVs90D9Hw"},"_spriteFrame":{"__uuid__":"8dAjeDPC1Fya0dwmN9d9/8"},"totalParticles":20,"life":3,"lifeVar":1,"_startColor":{"__type__":"cc.Color","r":255,"g":255,"b":255},"_startColorVar":{"__type__":"cc.Color","a":0},"_endColor":{"__type__":"cc.Color","r":255,"g":255,"b":255},"_endColorVar":{"__type__":"cc.Color","a":0},"angleVar":80,"startSize":100,"startSizeVar":50,"endSize":150,"endSizeVar":30,"startSpin":180,"endSpin":40,"posVar":{"__type__":"cc.Vec2","x":800},"gravity":{"__type__":"cc.Vec2","y":-300},"speed":0,"speedVar":0,"tangentialAccel":130,"tangentialAccelVar":40}],"_prefab":{"__type__":"cc.PrefabInfo","root":{"__id__":1},"asset":{"__uuid__":"c2AyW62rBJVYuleZaINKoX"},"fileId":"3cxt341CVMqL4kwETo8/6N"},"_trs":{"__type__":"TypedArray","ctor":"Float64Array","array":[-71.614,1011.849,0,0,0,0,1,1,1,1]}},{"__type__":"cc.Node","_name":"Effect_CharacterAni_Flower","_parent":{"__id__":2},"_components":[{"__type__":"cc.ParticleSystem","node":{"__id__":3},"_materials":[{"__uuid__":"ecpdLyjvZBwrvm+cedCcQy"}],"_custom":true,"_spriteFrame":{"__uuid__":"58oX5pWf9IdarG98tVVzlJ"},"totalParticles":30,"life":3,"lifeVar":1,"_startColor":{"__type__":"cc.Color","r":255,"g":255,"b":255},"_startColorVar":{"__type__":"cc.Color","a":0},"_endColor":{"__type__":"cc.Color","r":255,"g":255,"b":255},"_endColorVar":{"__type__":"cc.Color","a":0},"angle":70,"angleVar":29,"startSize":80,"startSizeVar":15,"endSize":50,"endSizeVar":20,"startSpin":120,"startSpinVar":40,"endSpin":270,"endSpinVar":40,"posVar":{"__type__":"cc.Vec2","x":800},"_positionType":2,"positionType":2,"gravity":{"__type__":"cc.Vec2","y":-450},"speed":40,"speedVar":0,"tangentialAccel":140,"tangentialAccelVar":50}],"_prefab":{"__type__":"cc.PrefabInfo","root":{"__id__":1},"asset":{"__uuid__":"c2AyW62rBJVYuleZaINKoX"},"fileId":"87TlMrYxhBiY1bJvuilj9w"},"_trs":{"__type__":"TypedArray","ctor":"Float64Array","array":[5.261,0,0,0,0,0,1,1,1,1]}}],[{"__type__":"cc.Prefab","_name":"ClearEffect_Bubble_Front","data":{"__id__":1}},{"__type__":"cc.Node","_name":"BubbleEffect","_children":[{"__id__":2}],"_components":[{"__type__":"a94f6q6ywJKyIwexIJ/NTD+","node":{"__id__":1},"awakeAudio":{"__uuid__":"b6WyW/xCdPkrebX0u5QD6U"}}],"_prefab":{"__type__":"cc.PrefabInfo","root":{"__id__":1},"asset":{"__uuid__":"d3DQd4fpdHnq09tV1UYg1B"},"fileId":"82Ifwf0VFG9qNv798deTMP"},"_trs":{"__type__":"TypedArray","ctor":"Float64Array","array":[0,0,0,0,0,0,1,1,1,1]}},{"__type__":"cc.Node","_name":"Effect_CharacterAni_Bubble","_parent":{"__id__":1},"_components":[{"__type__":"cc.ParticleSystem","node":{"__id__":2},"_materials":[{"__uuid__":"ecpdLyjvZBwrvm+cedCcQy"}],"_custom":true,"_file":{"__uuid__":"be6iz+eAZA661wXwB0QsRq"},"_spriteFrame":{"__uuid__":"9c5cFajMpIM46M2By7h/cj"},"totalParticles":3,"emissionRate":24.666666666666668,"life":1.5,"lifeVar":0.5,"_startColor":{"__type__":"cc.Color","r":255,"g":255,"b":255},"_startColorVar":{"__type__":"cc.Color","b":63},"_endColor":{"__type__":"cc.Color","r":255,"g":255,"b":255},"_endColorVar":{"__type__":"cc.Color","a":0},"angle":0,"angleVar":0,"startSize":100,"startSizeVar":20,"endSize":120,"endSizeVar":120,"posVar":{"__type__":"cc.Vec2","x":500,"y":900},"gravity":{"__type__":"cc.Vec2","y":150},"speed":-10,"speedVar":10,"tangentialAccel":0,"startRadius":100,"endRadius":200}],"_prefab":{"__type__":"cc.PrefabInfo","root":{"__id__":1},"asset":{"__uuid__":"d3DQd4fpdHnq09tV1UYg1B"},"fileId":"f6Ax3dKCFI0p9kH7AUZBJM"},"_trs":{"__type__":"TypedArray","ctor":"Float64Array","array":[0,0,0,0,0,0,1,1,1,1]}}],[{"__type__":"cc.Prefab","_name":"ClearEffect_Ballon_Back","data":{"__id__":1}},{"__type__":"cc.Node","_name":"BallonEffect","_children":[{"__id__":2}],"_components":[{"__type__":"a94f6q6ywJKyIwexIJ/NTD+","node":{"__id__":1},"awakeAudio":{"__uuid__":"d8ZvV4ZcZMJJfn/8sWCAlV"}}],"_prefab":{"__type__":"cc.PrefabInfo","root":{"__id__":1},"asset":{"__uuid__":"d6GhpE6aRCeaIYRDi/9b/X"},"fileId":"3cgeMlnlJN1Kl9lD8paOBP"},"_trs":{"__type__":"TypedArray","ctor":"Float64Array","array":[0,0,0,0,0,0,1,1,1,1]}},{"__type__":"cc.Node","_name":"Effect_CharacterAni_Balloon","_parent":{"__id__":1},"_children":[{"__id__":3},{"__id__":4}],"_components":[{"__type__":"cc.ParticleSystem","node":{"__id__":2},"_materials":[{"__uuid__":"ecpdLyjvZBwrvm+cedCcQy"}],"_custom":true,"_file":{"__uuid__":"e77Tlt6vtPr5tRRROvApBB"},"_spriteFrame":{"__uuid__":"8atiUC9KtBib1cKV8D7+Sn"},"totalParticles":3,"emissionRate":20,"life":2,"lifeVar":1,"_startColor":{"__type__":"cc.Color","r":255,"g":255,"b":255},"_startColorVar":{"__type__":"cc.Color","b":63,"a":0},"_endColor":{"__type__":"cc.Color","r":255,"g":255,"b":255},"_endColorVar":{"__type__":"cc.Color","a":0},"angle":0,"angleVar":0,"startSize":300,"endSize":450,"endSizeVar":200,"posVar":{"__type__":"cc.Vec2","x":600},"_positionType":1,"positionType":1,"gravity":{"__type__":"cc.Vec2","y":350},"speed":30,"speedVar":0,"tangentialAccel":0}],"_prefab":{"__type__":"cc.PrefabInfo","root":{"__id__":1},"asset":{"__uuid__":"d6GhpE6aRCeaIYRDi/9b/X"},"fileId":"84i2RNoJFJu4lJ7hwm1yQp"},"_trs":{"__type__":"TypedArray","ctor":"Float64Array","array":[0,-960,0,0,0,0,1,1,1,1]}},{"__type__":"cc.Node","_name":"Effect_Balloon_Yellow","_parent":{"__id__":2},"_components":[{"__type__":"cc.ParticleSystem","node":{"__id__":3},"_materials":[{"__uuid__":"ecpdLyjvZBwrvm+cedCcQy"}],"_custom":true,"_file":{"__uuid__":"e77Tlt6vtPr5tRRROvApBB"},"_spriteFrame":{"__uuid__":"b01H8iTjdPIb7A4+jIfCnC"},"totalParticles":4,"emissionRate":20,"life":3,"lifeVar":1,"_startColor":{"__type__":"cc.Color","r":255,"g":255,"b":255},"_startColorVar":{"__type__":"cc.Color","b":63,"a":0},"_endColor":{"__type__":"cc.Color","r":255,"g":255,"b":255},"_endColorVar":{"__type__":"cc.Color","a":0},"angle":0,"angleVar":0,"startSize":300,"endSize":450,"endSizeVar":200,"posVar":{"__type__":"cc.Vec2","x":600},"_positionType":1,"positionType":1,"gravity":{"__type__":"cc.Vec2","y":250},"speed":50,"speedVar":25,"tangentialAccel":0}],"_prefab":{"__type__":"cc.PrefabInfo","root":{"__id__":1},"asset":{"__uuid__":"d6GhpE6aRCeaIYRDi/9b/X"},"fileId":"dcpEhHyDFBvINk/bdnJRte"},"_trs":{"__type__":"TypedArray","ctor":"Float64Array","array":[0,-135.179,0,0,0,0,1,1,1,1]}},{"__type__":"cc.Node","_name":"Effect_Balloon_Red","_parent":{"__id__":2},"_components":[{"__type__":"cc.ParticleSystem","node":{"__id__":4},"_materials":[{"__uuid__":"ecpdLyjvZBwrvm+cedCcQy"}],"_custom":true,"_file":{"__uuid__":"e77Tlt6vtPr5tRRROvApBB"},"_spriteFrame":{"__uuid__":"2cCGDzXIVI1qrbcQA+HI2U"},"totalParticles":5,"emissionRate":20,"life":3,"lifeVar":1,"_startColor":{"__type__":"cc.Color","r":255,"g":255,"b":255},"_startColorVar":{"__type__":"cc.Color","b":63,"a":0},"_endColor":{"__type__":"cc.Color","r":255,"g":255,"b":255},"_endColorVar":{"__type__":"cc.Color","a":0},"angle":0,"angleVar":0,"startSize":300,"endSize":450,"endSizeVar":200,"posVar":{"__type__":"cc.Vec2","x":600},"_positionType":1,"positionType":1,"gravity":{"__type__":"cc.Vec2","y":300},"speed":80,"speedVar":40,"tangentialAccel":0}],"_prefab":{"__type__":"cc.PrefabInfo","root":{"__id__":1},"asset":{"__uuid__":"d6GhpE6aRCeaIYRDi/9b/X"},"fileId":"da6pT2+fxCFZ/+2BYbvMSm"},"_trs":{"__type__":"TypedArray","ctor":"Float64Array","array":[0,-165.076,0,0,0,0,1,1,1,1]}}],{"__type__":"cc.AudioClip","_name":"POGO_BGM","_native":".mp3","duration":18.337959,"loadMode":1},{"__type__":"cc.AudioClip","_name":"UI_BlockSwitch","_native":".mp3","duration":0.10449,"loadMode":1},[{"__type__":"cc.Prefab","_name":"sheep_Animation","data":{"__id__":1}},{"__type__":"cc.Node","_name":"sheep_Animation","_components":[{"__type__":"sp.Skeleton","node":{"__id__":1},"_materials":[{"__uuid__":"7a/QZLET9IDreTiBfRn2PD"}],"defaultSkin":"default","_preCacheMode":0,"loop":false,"_animationName":"animation","_playTimes":1,"_N$skeletonData":{"__uuid__":"bbxi1CVE5GFqYOEkhrvEHt"}},{"__type__":"86dc4nEm59BWrr2WoC5IuiM","node":{"__id__":1},"type":3,"animationName":"animation"}],"_prefab":{"__type__":"cc.PrefabInfo","root":{"__id__":1},"asset":{"__uuid__":"e2Dr185OlABKJXRLmfnWLO"},"fileId":"52W19aYGZABqpDwCVX5xru"},"_contentSize":{"__type__":"cc.Size","width":695,"height":640},"_trs":{"__type__":"TypedArray","ctor":"Float64Array","array":[0,0,0,0,0,0,1,1,1,1]}}],[{"__type__":"cc.Prefab","_name":"Tile","data":{"__id__":1}},{"__type__":"cc.Node","_name":"Tile","_children":[{"__id__":2}],"_components":[{"__id__":3},{"__type__":"e7028DGbiFM7ZY6anMaG4yA","node":{"__id__":1},"iconNode":{"__id__":2},"animator":{"__id__":3}}],"_prefab":{"__type__":"cc.PrefabInfo","root":{"__id__":1},"asset":{"__uuid__":"e7XNovCANHLZ7rjsNdEK66"},"fileId":"a0zD4LD9RMAZd65kzvq1z+"},"_contentSize":{"__type__":"cc.Size","width":140,"height":140},"_trs":{"__type__":"TypedArray","ctor":"Float64Array","array":[0,0,0,0,0,0,1,1,1,1]}},{"__type__":"cc.Node","_name":"Icon","_parent":{"__id__":1},"_prefab":{"__type__":"cc.PrefabInfo","root":{"__id__":1},"asset":{"__uuid__":"e7XNovCANHLZ7rjsNdEK66"},"fileId":"c6o51pW5NP0Ydgt4Pez0Aq"},"_contentSize":{"__type__":"cc.Size","width":140,"height":140},"_trs":{"__type__":"TypedArray","ctor":"Float64Array","array":[0,0,0,0,0,0,1,1,1,1]}},{"__type__":"cc.Animation","node":{"__id__":1},"_clips":[{"__uuid__":"f4Zj+x5ARLU5/ZaBww1Ld4"},{"__uuid__":"1bFGXL3ZhN7YBtYv5QJdjb"},{"__uuid__":"2c3EWlmVRBfoA4Ye4j5nY7"},{"__uuid__":"b0QBoZdsNHmLF3zqI7WWTZ"}]}],{"__type__":"cc.AnimationClip","_name":"Awake","_duration":0.08333333333333333,"curveData":{"paths":{"Icon":{"props":{"y":[{"frame":0,"value":70,"curve":"linear"},{"frame":0.08333333333333333,"value":0}]}}}}},[{"__type__":"cc.Prefab","_name":"ClearEffect_Ballon_Front","data":{"__id__":1}},{"__type__":"cc.Node","_name":"ClearEffect_Ballon_Front","_children":[{"__id__":2}],"_components":[{"__type__":"a94f6q6ywJKyIwexIJ/NTD+","node":{"__id__":1},"awakeAudio":{"__uuid__":"d8ZvV4ZcZMJJfn/8sWCAlV"}}],"_prefab":{"__type__":"cc.PrefabInfo","root":{"__id__":1},"asset":{"__id__":0},"fileId":"8cmaTXm4tE1qTztvjwWqaY"},"_trs":{"__type__":"TypedArray","ctor":"Float64Array","array":[0,0,0,0,0,0,1,1,1,1]}},{"__type__":"cc.Node","_name":"Effect_CharacterAni_Balloon","_parent":{"__id__":1},"_children":[{"__id__":3},{"__id__":4}],"_components":[{"__type__":"cc.ParticleSystem","node":{"__id__":2},"_materials":[{"__uuid__":"ecpdLyjvZBwrvm+cedCcQy"}],"_custom":true,"_file":{"__uuid__":"e77Tlt6vtPr5tRRROvApBB"},"_spriteFrame":{"__uuid__":"8atiUC9KtBib1cKV8D7+Sn"},"totalParticles":1,"emissionRate":4,"life":2,"lifeVar":1,"_startColor":{"__type__":"cc.Color","r":255,"g":255,"b":255},"_startColorVar":{"__type__":"cc.Color","b":63,"a":0},"_endColor":{"__type__":"cc.Color","r":255,"g":255,"b":255},"_endColorVar":{"__type__":"cc.Color","a":0},"angle":0,"angleVar":0,"startSize":300,"endSize":450,"endSizeVar":200,"posVar":{"__type__":"cc.Vec2","x":600},"_positionType":1,"positionType":1,"gravity":{"__type__":"cc.Vec2","y":350},"speed":30,"speedVar":0,"tangentialAccel":0}],"_prefab":{"__type__":"cc.PrefabInfo","root":{"__id__":1},"asset":{"__id__":0},"fileId":"d48uucDhFLjpfdwx/b0PQU"},"_trs":{"__type__":"TypedArray","ctor":"Float64Array","array":[0,-960,0,0,0,0,1,1,1,1]}},{"__type__":"cc.Node","_name":"Effect_Balloon_Yellow","_parent":{"__id__":2},"_components":[{"__type__":"cc.ParticleSystem","node":{"__id__":3},"_materials":[{"__uuid__":"ecpdLyjvZBwrvm+cedCcQy"}],"_custom":true,"_file":{"__uuid__":"e77Tlt6vtPr5tRRROvApBB"},"_spriteFrame":{"__uuid__":"b01H8iTjdPIb7A4+jIfCnC"},"totalParticles":2,"emissionRate":4,"life":3,"lifeVar":1,"_startColor":{"__type__":"cc.Color","r":255,"g":255,"b":255},"_startColorVar":{"__type__":"cc.Color","b":63,"a":0},"_endColor":{"__type__":"cc.Color","r":255,"g":255,"b":255},"_endColorVar":{"__type__":"cc.Color","a":0},"angle":0,"angleVar":0,"startSize":300,"endSize":450,"endSizeVar":200,"posVar":{"__type__":"cc.Vec2","x":600},"_positionType":1,"positionType":1,"gravity":{"__type__":"cc.Vec2","y":250},"speed":50,"speedVar":25,"tangentialAccel":0}],"_prefab":{"__type__":"cc.PrefabInfo","root":{"__id__":1},"asset":{"__id__":0},"fileId":"56sXC+7w5F8IK+l2QeVPFo"},"_trs":{"__type__":"TypedArray","ctor":"Float64Array","array":[0,-135.179,0,0,0,0,1,1,1,1]}},{"__type__":"cc.Node","_name":"Effect_Balloon_Red","_parent":{"__id__":2},"_components":[{"__type__":"cc.ParticleSystem","node":{"__id__":4},"_materials":[{"__uuid__":"ecpdLyjvZBwrvm+cedCcQy"}],"_custom":true,"_file":{"__uuid__":"e77Tlt6vtPr5tRRROvApBB"},"_spriteFrame":{"__uuid__":"2cCGDzXIVI1qrbcQA+HI2U"},"totalParticles":2,"emissionRate":4,"life":3,"lifeVar":1,"_startColor":{"__type__":"cc.Color","r":255,"g":255,"b":255},"_startColorVar":{"__type__":"cc.Color","b":63,"a":0},"_endColor":{"__type__":"cc.Color","r":255,"g":255,"b":255},"_endColorVar":{"__type__":"cc.Color","a":0},"angle":0,"angleVar":0,"startSize":300,"endSize":450,"endSizeVar":200,"posVar":{"__type__":"cc.Vec2","x":600},"_positionType":1,"positionType":1,"gravity":{"__type__":"cc.Vec2","y":300},"speed":80,"speedVar":40,"tangentialAccel":0}],"_prefab":{"__type__":"cc.PrefabInfo","root":{"__id__":1},"asset":{"__id__":0},"fileId":"7bAjJIlU1B+J6aJmhOQutg"},"_trs":{"__type__":"TypedArray","ctor":"Float64Array","array":[0,-165.076,0,0,0,0,1,1,1,1]}}]]